phyfum/__about__.py
phyfum/__init__.py
phyfum/__main__.py
phyfum/snk.yaml
phyfum/cli/__init__.py
phyfum/workflow/Snakefile
phyfum/workflow/config.schema.yml
phyfum/workflow/aux/checkConfig.py
phyfum/workflow/aux/checkInput.py
phyfum/workflow/aux/checkPatients.py
phyfum/workflow/aux/createXML.py
phyfum/workflow/aux/gatherMLE.sh
phyfum/workflow/aux/integratingOverS.R
phyfum/workflow/aux/methCNV.R
phyfum/workflow/aux/methylationBetas2xml.py
phyfum/workflow/aux/mixingAndConvergence.R
phyfum/workflow/aux/modelSelectionS.R
phyfum/workflow/aux/plot_posterior_predictive.py
phyfum/workflow/aux/plot_tree.R
phyfum/workflow/aux/readIDAT.R
phyfum/workflow/aux/readInputMethylation.py
phyfum/workflow/aux/select_cpgs.py
phyfum/workflow/aux/validate_beast.py
phyfum/workflow/data/13059_2016_1066_MOESM1_ESM.csv
phyfum/workflow/data/MethylationEPIC_v-1-0_B4.csv
phyfum-0.6.1.dist-info/METADATA
phyfum-0.6.1.dist-info/WHEEL
phyfum-0.6.1.dist-info/entry_points.txt
phyfum-0.6.1.dist-info/licenses/LICENSE.txt
phyfum-0.6.1.dist-info/RECORD
