Metadata-Version: 2.4
Name: phyfum
Version: 0.6.1
Project-URL: Documentation, https://github.com/unknown/phyfum#readme
Project-URL: Issues, https://github.com/pbousquets/phyfum/issues
Project-URL: Source, https://github.com/pbousquets/phyfum
Author-email: pbousquets <pbousquetsm@gmail.com>
License-Expression: MIT
License-File: LICENSE.txt
Classifier: Development Status :: 4 - Beta
Classifier: Programming Language :: Python
Classifier: Programming Language :: Python :: 3.7
Classifier: Programming Language :: Python :: 3.8
Classifier: Programming Language :: Python :: 3.9
Classifier: Programming Language :: Python :: 3.10
Classifier: Programming Language :: Python :: 3.11
Classifier: Programming Language :: Python :: Implementation :: CPython
Classifier: Programming Language :: Python :: Implementation :: PyPy
Requires-Python: >=3.7
Requires-Dist: argparse
Requires-Dist: matplotlib
Requires-Dist: numpy
Requires-Dist: pandas
Requires-Dist: scipy
Requires-Dist: seaborn
Requires-Dist: snk
Requires-Dist: typing
Requires-Dist: yattag
